.hgignore
README.txt
setup.py
Products/__init__.py
Products.PloneHotfix20110531.egg-info/PKG-INFO
Products.PloneHotfix20110531.egg-info/SOURCES.txt
Products.PloneHotfix20110531.egg-info/dependency_links.txt
Products.PloneHotfix20110531.egg-info/namespace_packages.txt
Products.PloneHotfix20110531.egg-info/not-zip-safe
Products.PloneHotfix20110531.egg-info/requires.txt
Products.PloneHotfix20110531.egg-info/top_level.txt
Products/PloneHotfix20110531/__init__.py
Products/PloneHotfix20110531/tests.py