Metadata-Version: 1.0
Name: Products.PloneHotfix20110531
Version: 2.0
Summary: Plone critical security hotfix addressing multiple vulnerabilities
Home-page: http://plone.org/products/plone-hotfix/releases/20110531
Author: Plone security team
Author-email: security@plone.org
License: GPL
Keywords: security hotfix patch
Platform: UNKNOWN
Classifier: Programming Language :: Python
Classifier: Framework :: Plone
Classifier: Framework :: Zope2
